gitsubpull/__init__.py
gitsubpull/main.py
gitsubpull-0.1.0.dist-info/entry_points.txt
gitsubpull-0.1.0.dist-info/WHEEL
gitsubpull-0.1.0.dist-info/METADATA
gitsubpull-0.1.0.dist-info/RECORD
